tft/nucleus/api/__init__.py
tft/nucleus/api/about.py
tft/nucleus/api/crud.py
tft/nucleus/api/database.py
tft/nucleus/api/errors.py
tft/nucleus/api/internal.py
tft/nucleus/api/public.py
tft/nucleus/api/routers/__init__.py
tft/nucleus/api/routers/compose.py
tft/nucleus/api/routers/test_request.py
tft/nucleus/api/routers/user.py
tft/nucleus/api/schemes/__init__.py
tft/nucleus/api/schemes/compose.py
tft/nucleus/api/schemes/test_request.py
tft/nucleus/api/schemes/user.py
tft_api-0.0.2.dist-info/WHEEL
tft_api-0.0.2.dist-info/METADATA
tft_api-0.0.2.dist-info/RECORD
